[
  {
    "id": "patricia",
    "live": true,
    "tags": [
      "health",
      "mindfulness",
      "meditation",
      "relaxation"
    ]
  },
  {
    "id": "pirin-adventures",
    "live": true,
    "tags": [
      "health",
      "walking",
      "exercise",
      "hiking",
      "trekking",
      "snow shoe walking"
    ]
  },
  {
    "id": "oxo-schools",
    "live": false,
    "tags": [
      "health",
      "cycling",
      "exercise",
      "enduro",
      "mtb",
      "mountain biking"
    ]
  },
  {
    "id": "peak-fitness",
    "live": true,
    "tags": [
      "health",
      "running",
      "fitness",
      "exercise",
      "workout",
      "bootcamp"
    ]
  },
  {
    "id": "aqua-aerobics",
    "live": true,
    "tags": [
      "health",
      "exercise",
      "swimming",
      "aerobics"
    ]
  },
  {
    "id": "mtb-bansko",
    "live": true,
    "tags": [
      "health",
      "cycling",
      "exercise",
      "enduro",
      "mtb",
      "mountain biking",
      "road biking"
    ]
  },
  {
    "id": "vdm-international-eood",
    "live": true,
    "tags": [
      "accountancy",
      "administration",
      "management",
      "bookkeeping",
      "salaries",
      "companies"
    ]
  },
  {
    "id": "bansko-tourist-information",
    "live": true,
    "tags": [
      "apartment rental advice",
      "transfer",
      "lift pass",
      "ski",
      "snowboard",
      "snowmobile",
      "mountain guide",
      "hiking",
      "cycling",
      "exercise",
      "mtb",
      "mountain biking",
      "road biking"
    ]
  }
]